{
	"id": "e935fc43-6c57-4ebf-901c-00f2b1589d54",
	"name": "Prod",
	"values": [
		{
			"key": "API Gateway User Session Token",
			"value": "",
			"type": "secret",
			"enabled": true
		},
		{
			"key": "API Gateway User API Token",
			"value": "long token",
			"type": "secret",
			"enabled": true
		},
		{
			"key": "API Gateway Domain",
			"value": "https://www.apigatewaydomain.sbs",
			"type": "default",
			"enabled": true
		},
		{
			"key": "cc_domain",
			"value": "client.domaindomain.com",
			"type": "default",
			"enabled": true
		},
		{
			"key": "CC User Session Token",
			"value": "",
			"type": "default",
			"enabled": true
		},
		{
			"key": "CC User API Token",
			"value": "anotherToken",
			"type": "default",
			"enabled": true
		},
		{
			"key": "facade_domain",
			"value": "www.myfacadeweb.diy",
			"type": "default",
			"enabled": true
		},
		{
			"key": "Facade Web API Token",
			"value": "longtoken",
			"type": "secret",
			"enabled": true
		},
		{
			"key": "cc_facade_domain",
			"value": "facade.domaindomain.info",
			"type": "default",
			"enabled": true
		}
	],
	"_postman_variable_scope": "environment",
	"_postman_exported_at": "2025-03-06T13:38:42.175Z",
	"_postman_exported_using": "Postman/11.35.3"
}